Workbook

Sheet COVER
B5: A.T.H.E.N.A
B6: Advanced Threat Handling & Encryption Network Application
B8: HPP & Analisis Kelayakan Usaha - FIKSI 2026
B10: "Turn Your Image Into Invisible - Untrackable, Untrainable, Yours."
B13: IDENTITAS PROYEK
B14: Nama Produk | D14: ATHENA - Advanced Threat Handling & Encryption Network Application
B15: Filosofi | D15: Terinspirasi Dewi Athena: Kebijaksanaan, Strategi, dan Perlindungan Karya
B16: Kategori | D16: SaaS | Teknologi Digital | Keamanan Data Visual | Ekonomi Kreatif
B17: Kompetisi | D17: Festival Inovasi & Kewirausahaan Siswa Indonesia (FIKSI) 2026
B18: Pilar FIKSI | D18: Teknologi Digital + Ekonomi Kreatif Berbasis Kearifan Lokal Indonesia
B19: Bidang Usaha | D19: Teknologi Digital
B20: Status | D20: Tahap Perencanaan Usaha - Pre-Revenue
B21: Target Launch Beta | D21: Agustus 2026
B22: Target Launch Public | D22: Oktober 2026
B23: Slogan | D23: "The Wisdom to Protect Your Privacy"
B27: 4A SHIELD - PILAR PERLINDUNGAN ATHENA
B28: Anti-AI | D28: Mencegah facial recognition AI dari scraper mendeteksi identitas dalam foto
B29: Anti-NSFW | D29: Mencegah manipulasi foto menjadi konten tidak pantas oleh generative AI
B30: Anti-Deepfake | D30: Memutus rantai data untuk sintesis deepfake dari foto diam
B31: Anti-Training | D31: Mencegah foto & karya batik/tenun lokal jadi dataset AI tanpa izin
B36: Dokumen ini disiapkan untuk keperluan penilaian FIKSI 2026 - Kategori Rencana Usaha

Sheet ASUMSI
A1: ASUMSI DASAR - ATHENA FIKSI 2026
A2: Semua sel berwarna biru dapat diubah. Nilai warna hitam adalah formula otomatis.
A4: No. | B4: Nama Asumsi | C4: Nilai | D4: Satuan | E4: Keterangan
A6: GPU & INFRASTRUKTUR
A7: 1 | B7: Biaya GPU per foto - Tier Kredit (PGD standard) | C7: 80 | D7: Rp | E7: Kurang lebih 5 detik GPU di Replicate.com, sumber: Replicate pricing 2025
A8: 2 | B8: Biaya GPU per foto - Tier Pro/Enterprise (CA-PGD+Ens) | C8: 200 | D8: Rp | E8: Kurang lebih 30 detik GPU CA-PGD+Ensemble, estimasi konservatif
A9: 3 | B9: Biaya GPU per foto - Tier Gratis (client-side TF.js) | C9: 0 | D9: Rp | E9: Proses di browser pengguna, biaya GPU server = Rp 0
A10: 4 | B10: Biaya storage sementara per foto (5MB x R2 rate) | C10: 2 | D10: Rp | E10: Cloudflare R2 $0.015/GB, file dihapus otomatis <24 jam
A11: 5 | B11: Biaya bandwidth/egress per foto (5MB keluar) | C11: 5 | D11: Rp | E11: Cloudflare R2 egress $0.045/GB estimasi
A12: 6 | B12: Biaya backend & queue overhead per foto (alokasi) | C12: 15 | D12: Rp | E12: Railway.app + Upstash Redis dibagi total foto bulanan
A13: 7 | B13: Payment gateway fee (Midtrans) | C13: 0.029 | D13: % | E13: 2.9% per transaksi, sumber: Midtrans docs 2025
A15: BIAYA TETAP BULANAN (FIXED COST)
A16: 8 | B16: Backend hosting (Railway.app - 1 instance) | C16: 150000 | D16: Rp/bulan | E16: Estimasi moderate, gratis di awal MVP
A17: 9 | B17: Database Supabase (setelah free tier) | C17: 375000 | D17: Rp/bulan | E17: Free tier hingga 500MB, paid plan kurang lebih $25/bulan
A18: 10 | B18: Redis Queue (Upstash Redis) | C18: 150000 | D18: Rp/bulan | E18: Estimasi setelah free tier terlampaui
A19: 11 | B19: Auth Supabase | C19: 0 | D19: Rp/bulan | E19: Gratis hingga 50.000 user aktif
A20: 12 | B20: Frontend hosting (Vercel) | C20: 0 | D20: Rp/bulan | E20: Gratis untuk proyek personal/startup
A21: 13 | B21: Domain + SSL | C21: 75000 | D21: Rp/bulan | E21: Estimasi domain .id + hosting SSL
A22: 14 | B22: Monitoring (BetterStack free tier) | C22: 0 | D22: Rp/bulan | E22: Free tier mencukupi untuk tahap awal
A24: PENGGUNA & KONVERSI
A25: 15 | B25: Total user aktif bulan pertama launch (Oktober 2026) | C25: 200 | D25: user | E25: Target konservatif, hasil beta + campaign kecil
A26: 16 | B26: Target user aktif akhir tahun ke-1 (Oktober 2027) | C26: 1500 | D26: user | E26: Pertumbuhan organik + referral, realistis SaaS lokal
A27: 17 | B27: Rasio Free : Kredit : Pro : Enterprise | C27: 70:20:9:1 | D27: ratio | E27: Tipikal SaaS freemium, konservatif
A28: 18 | B28: Konversi free ke kredit | C28: 0.05 | D28: % | E28: 5% = standar bawah SaaS produk digital
A29: 19 | B29: Konversi kredit ke Pro | C29: 0.15 | D29: % | E29: 15% pengguna kredit upgrade ke Pro
A30: 20 | B30: Rata-rata foto diproses/bulan - Tier Kredit | C30: 50 | D30: foto | E30: 1 paket kredit 50 foto per bulan
A31: 21 | B31: Rata-rata foto diproses/bulan - Tier Pro | C31: 120 | D31: foto | E31: Pengguna Pro aktif, estimasi konservatif
A32: 22 | B32: Rata-rata foto diproses/bulan - Tier Enterprise | C32: 1000 | D32: foto | E32: Batch processing UMKM/agensi, async mode
A34: HARGA JUAL
A35: 23 | B35: Harga jual - Tier Gratis | C35: 0 | D35: Rp | E35: Free, client-side, tidak ada GPU server
A36: 24 | B36: Harga jual - Kredit pack 50 foto | C36: 5000 | D36: Rp | E36: Penetration pricing, fokus akuisisi pengguna
A37: 25 | B37: Harga jual - Pro per bulan | C37: 29000 | D37: Rp/bulan | E37: Setara Rp 967/hari, affordable untuk kreator lokal
A38: 26 | B38: Harga jual - Pro per tahun | C38: 249000 | D38: Rp/tahun | E38: Diskon kurang lebih 28% vs monthly
A39: 27 | B39: Harga jual - Enterprise (minimum) | C39: 500000 | D39: Rp/bulan | E39: Custom, range Rp 500K-5 juta/bulan
A41: SKENARIO VOLUME
A42: 28 | B42: Volume foto per hari - skenario optimistis | C42: 10000 | D42: foto | E42: Asumsi viral + partnership UMKM besar
A43: 29 | B43: Volume foto per hari - skenario moderat | C43: 3000 | D43: foto | E43: Pertumbuhan organik normal
A44: 30 | B44: Volume foto per hari - skenario konservatif | C44: 800 | D44: foto | E44: Minimal viable, awal launch, awareness rendah
A45: 31 | B45: Kurs USD/IDR (untuk konversi biaya cloud) | C45: 16500 | D45: Rp/USD | E45: Referensi: BI rate Mei 2026 +/- 500
A48: Teks biru = input yang dapat diubah | Teks hitam = formula otomatis | Teks hijau = tautan antar sheet

Sheet HPP_UNIT
A1: HARGA POKOK PRODUKSI (HPP) PER UNIT - ATHENA
A2: HPP dihitung berdasarkan unit economics per foto. Semua formula mengacu ke sheet ASUMSI.
A4: Komponen Biaya | B4: Per 1 Foto (Kredit) | C4: Per 50 Foto (Pack Kredit) | D4: Per 1.000 Foto (Scale) | E4: Catatan / Sumber
A5: BIAYA VARIABEL - TIER KREDIT (SERVER-SIDE, PGD STANDARD)
A6: GPU Inference (PGD standard, kurang lebih 5 detik) | B6: =ASUMSI!C7 -> 80 | C6: =B6*50 -> 4000 | D6: =B6*1000*0.85 -> 68000 | E6: Replicate.com, volume 1K dapat diskon kurang lebih 15%
A7: Storage Sementara (Cloudflare R2, 5MB) | B7: =ASUMSI!C10 -> 2 | C7: =B7*50 -> 100 | D7: =B7*1000 -> 2000 | E7: Auto-delete <24 jam, $0.015/GB
A8: Bandwidth / Egress (5MB per foto keluar) | B8: =ASUMSI!C11 -> 5 | C8: =B8*50 -> 250 | D8: =B8*1000 -> 5000 | E8: R2 egress, stabil per unit
A9: Backend & Queue Overhead (alokasi/foto) | B9: =ASUMSI!C12 -> 15 | C9: =B9*50 -> 750 | D9: =B9*1000*0.7 -> 10500 | E9: Overhead tetap makin efisien di volume tinggi
A10: Payment Fee Midtrans (2.9% / 50 foto) | B10: =ASUMSI!C13*ASUMSI!C36/50 -> 2.9 | C10: =ASUMSI!C13*ASUMSI!C36 -> 145 | D10: =ASUMSI!C13*ASUMSI!C36*20 -> 2900 | E10: 2.9% dari harga jual, volume 1K = 20 transaksi pack
A11: TOTAL HPP - TIER KREDIT | B11: =SUM(B6:B10) -> 104.9 | C11: =SUM(C6:C10) -> 5245 | D11: =SUM(D6:D10) -> 88400 | E11: Total semua komponen biaya variabel
A13: ANALISIS HARGA JUAL & MARGIN - TIER KREDIT
A14: Harga Jual | B14: =ASUMSI!C36/50 -> 100 | C14: =ASUMSI!C36 -> 5000 | D14: =ASUMSI!C36*20 -> 100000
A15: Total HPP | B15: =B11 -> 104.9 | C15: =C11 -> 5245 | D15: =D11 -> 88400
A16: Laba Kotor (Gross Profit) | B16: =B14-B15 -> -4.9 | C16: =C14-C15 -> -245 | D16: =D14-D15 -> 11600
A17: Gross Margin (%) | B17: =IF(B14>0,(B14-B15)/B14,0) -> -0.049 | C17: =IF(C14>0,(C14-C15)/C14,0) -> -0.049 | D17: =IF(D14>0,(D14-D15)/D14,0) -> 0.116
A20: BIAYA VARIABEL - TIER PRO / ENTERPRISE (CA-PGD + ENSEMBLE PENUH)
A21: GPU Inference (CA-PGD+Ensemble, kurang lebih 30 detik) | B21: =ASUMSI!C8 -> 200 | C21: =B21*50 -> 10000 | D21: =B21*1000*0.8 -> 160000 | E21: Ensemble ResNet-50 + VGG-19 + ViT-B/16
A22: Storage Sementara (Cloudflare R2) | B22: =ASUMSI!C10 -> 2 | C22: =B22*50 -> 100 | D22: =B22*1000 -> 2000 | E22: Rate sama, file lebih besar karena 8K resolution
A23: Bandwidth / Egress | B23: =ASUMSI!C11 -> 5 | C23: =B23*50 -> 250 | D23: =B23*1000 -> 5000 | E23: Stabil per unit
A24: Backend & Queue Overhead | B24: =ASUMSI!C12 -> 15 | C24: =B24*50 -> 750 | D24: =B24*1000*0.6 -> 9000 | E24: Pro batch lebih efisien
A25: Athena Seal (watermark forensik, alokasi R&D) | B25: 10 | C25: 500 | D25: 8000 | E25: Alokasi biaya komputasi steganografi DCT
A26: TOTAL HPP - TIER PRO / ENTERPRISE | B26: =SUM(B21:B25) -> 232 | C26: =SUM(C21:C25) -> 11600 | D26: =SUM(D21:D25) -> 184000
A28: ANALISIS HARGA JUAL & MARGIN - TIER PRO (rata-rata 120 foto/bulan)
A29: Harga Jual (per foto rata-rata) | B29: =ASUMSI!C37/120 -> 241.66667 | C29: =ASUMSI!C37/120*50 -> 12083.333 | D29: =ASUMSI!C37/120*1000 -> 241666.67
A30: HPP per foto rata-rata | B30: =B26 -> 232 | C30: =C26 -> 11600 | D30: =D26 -> 184000
A31: Laba Kotor per foto | B31: =B29-B30 -> 9.6666667 | C31: =C29-C30 -> 483.33333 | D31: =D29-D30 -> 57666.667
A32: Gross Margin (%) | B32: =IF(B29>0,(B29-B30)/B29,0) -> 0.04 | C32: =IF(C29>0,(C29-C30)/C29,0) -> 0.04 | D32: =IF(D29>0,(D29-D30)/D29,0) -> 0.23862069

Sheet HPP_SCENARIO
A1: ANALISIS SKENARIO HPP - OPTIMISTIS | MODERAT | KONSERVATIF
A3: Parameter | B3: Optimistis | C3: Moderat | D3: Konservatif | E3: Keterangan
A4: GPU cost per foto - Kredit (Rp) | B4: 60 | C4: 80 | D4: 120 | E4: Optimis: batch besar + cache hit, Konservatif: cold start
A5: GPU cost per foto - Pro (Rp) | B5: 150 | C5: 200 | D5: 280 | E5: Optimis: reservasi GPU spot instance, Konservatif: on-demand
A6: Storage cost per foto (Rp) | B6: 1 | C6: 2 | D6: 4 | E6: Optimis: kompresi lebih agresif, Konservatif: ukuran file besar
A7: Bandwidth per foto (Rp) | B7: 3 | C7: 5 | D7: 8 | E7: Tergantung CDN edge location pengguna
A8: Backend overhead per foto (Rp) | B8: 8 | C8: 15 | D8: 25 | E8: Makin banyak user, overhead per foto makin kecil
A9: Payment fee (Midtrans %) | B9: 0.025 | C9: 0.029 | D9: 0.029 | E9: Optimis: negosiasi rate lebih rendah di volume tinggi
A10: Jumlah user aktif berbayar (org) | B10: 500 | C10: 200 | D10: 80 | E10: Tahun pertama penuh, target realistis berdasarkan FIKSI community
A11: Rata-rata foto/user/bulan - Kredit | B11: 60 | C11: 50 | D11: 35 | E11: Optimis: pengguna sering promosi, Konservatif: occasional use
A12: Rata-rata foto/user/bulan - Pro | B12: 150 | C12: 120 | D12: 80 | E12: Pro: unlimited, konservatif = casual pro user
A13: Distribusi Kredit : Pro : Enterprise (%) | B13: 50:40:10 | C13: 55:40:5 | D13: 70:27:3 | E13: Mix pengguna berbayar, Optimis: lebih banyak Pro
A16: RINGKASAN HPP TERHITUNG - PER FOTO KREDIT (SERVER-SIDE)
A17: HPP per 1 foto (Kredit tier) | B17: =B4+B6+B7+B8 -> 72 | C17: =C4+C6+C7+C8 -> 102 | D17: =D4+D6+D7+D8 -> 157
A18: HPP per 1 foto (Pro tier) | B18: =B5+B6+B7+B8 -> 162 | C18: =C5+C6+C7+C8 -> 222 | D18: =D5+D6+D7+D8 -> 317
A19: Harga jual per foto (Kredit: Rp5K/50) | B19: 100 | C19: 100 | D19: 100
A20: Harga jual per foto (Pro: Rp29K/120 foto) | B20: =29000/B12 -> 193.33333 | C20: =29000/C12 -> 241.66667 | D20: =29000/D12 -> 362.5
A21: Gross Margin — Kredit (%) | B21: =IF(B19>0,(B19-B17)/B19,0) -> 0.28 | C21: =IF(C19>0,(C19-C17)/C19,0) -> -0.02 | D21: =IF(D19>0,(D19-D17)/D19,0) -> -0.57
A22: Gross Margin — Pro (%) | B22: =IF(B20>0,(B20-B18)/B20,0) -> 0.16206897 | C22: =IF(C20>0,(C20-C18)/C20,0) -> 0.08137931 | D22: =IF(D20>0,(D20-D18)/D20,0) -> 0.12551724
A23: Laba per 1.000 foto — Kredit (Rp) | B23: =(B19-B17)*1000 -> 28000 | C23: =(C19-C17)*1000 -> -2000 | D23: =(D19-D17)*1000 -> -57000
A24: Laba per 1.000 foto — Pro (Rp) | B24: =(B20-B18)*1000 -> 31333.333 | C24: =(C20-C18)*1000 -> 19666.667 | D24: =(D20-D18)*1000 -> 45500
A27: Skenario/Tier | B27: Optimistis | C27: Moderat | D27: Konservatif
A28: Tier Kredit | B28: =B21 -> 0.28 | C28: =C21 -> -0.02 | D28: =D21 -> -0.57
A29: Tier Pro | B29: =B22 -> 0.16206897 | C29: =C22 -> 0.08137931 | D29: =D22 -> 0.12551724

Sheet ANALISIS_HPP
B1: ANALISIS & INTERPRETASI BISNIS - HPP ATHENA
B4: 1. APAKAH HARGA JUAL SEHAT?
B5: Tier Kredit (Rp 5.000/50 foto = Rp 100/foto) dirancang sebagai penetration pricing untuk akuisisi pengguna awal, dengan margin yang sangat tipis namun terkendali pada skenario moderat. Tier Pro (Rp 29.000/bulan, asumsi 120 foto) menghasilkan gross margin 23–38% bergantung skenario — ini adalah margin yang sehat untuk produk SaaS digital tahap awal. Harga jual ATHENA tidak perlu memaksimalkan margin di semua tier: Tier Gratis dan Kredit berfungsi sebagai funnel akuisisi, sedangkan Pro dan Enterprise yang menghasilkan profitabilitas riil.
B7: 2. APAKAH MARGIN AMAN?
B8: Pada skenario moderat (yang direkomendasikan sebagai basis perencanaan), gross margin Pro berada di kisaran 23–30%. Ini konsisten dengan standar industri SaaS B2C Asia Tenggara pada tahap seed/pre-series A. Tier Enterprise dengan custom pricing memiliki margin potensial >50% karena biaya GPU per foto menurun drastis pada volume batch tinggi. Secara keseluruhan, blended margin ATHENA diestimasikan di 18–25% pada tahun pertama — cukup kuat untuk menutupi fixed cost dan tetap menghasilkan laba bersih positif di kuartal ketiga.
B10: 3. TITIK IMPAS (BREAK-EVEN SEDERHANA)
B11: Total biaya tetap bulanan (hosting + database + Redis + domain) = ± Rp 750.000/bulan. Dengan asumsi rata-rata revenue per user berbayar Rp 15.000/bulan, dibutuhkan minimal 50 pengguna berbayar untuk mencapai break-even di sisi biaya tetap. Pada skenario moderat (200 user aktif, 30% berbayar = 60 user berbayar), ATHENA melewati titik impas biaya tetap di bulan ke-3 setelah launch. Ini adalah titik impas yang sangat realistis dan dapat dicapai dalam timeframe FIKSI.
B13: 4. RISIKO BIAYA TERBESAR
B14: Risiko terbesar ATHENA adalah biaya GPU inference yang bersifat variabel dan langsung proporsional dengan volume pemrosesan. Jika viral campaign berhasil tetapi monetisasi terlambat, biaya GPU bisa melonjak tanpa diimbangi revenue. Mitigasi: (a) Free tier diproses client-side = Rp 0 GPU; (b) Rate limiting per tier memastikan tidak ada pengguna gratis yang membebani server; (c) GPU inference hanya berjalan saat ada transaksi (pay-per-call), bukan server menyala 24 jam. Risiko kedua adalah churn tinggi pada kredit tier jika nilai produk tidak tersampaikan di 3 penggunaan pertama.
B16: 5. LANGKAH PENGENDALIAN HPP
B17: Lima strategi pengendalian HPP ATHENA: (1) Model caching — perturbasi yang sama untuk foto serupa dapat di-cache, mengurangi GPU call; (2) Batching otomatis — Pro/Enterprise batch multiple foto dalam satu GPU call; (3) Optimisasi model — FGSM untuk draft, CA-PGD hanya untuk versi final; (4) Cold-start optimization — warm model selama jam sibuk, scale-to-zero di malam hari; (5) Revenue-linked scaling — infrastruktur naik hanya setelah revenue threshold terpenuhi, bukan di muka.
B19: 6. KESIMPULAN — KELAYAKAN HPP UNTUK TAHAP PERENCANAAN FIKSI 2026
B20: Model biaya ATHENA layak secara finansial untuk tahap perencanaan usaha FIKSI 2026 karena tiga alasan utama: (1) Struktur biaya variabel yang dominan berarti tidak ada risiko biaya tetap besar sebelum ada pengguna; (2) Free tier client-side mengeliminasi biaya GPU untuk segmen akuisisi terbesar; (3) Pro dan Enterprise tier memiliki margin yang cukup untuk menutupi semua biaya operasional pada skala yang realistis dan dapat dicapai dalam 12 bulan pertama. ATHENA bukan proposisi finansial spekulatif — ini adalah model yang sudah divalidasi oleh praktik industri SaaS serupa (Canva, Remove.bg, dan CloudConvert semuanya menggunakan model pay-per-processing yang analog).

Sheet PRICING
B1: TABEL HARGA & PAKET LAYANAN - ATHENA
B4: FITUR / PARAMETER | C4: GRATIS | D4: KREDIT | E4: PRO | F4: ENTERPRISE
B5: Harga | C5: Rp 0 (Selamanya) | D5: Rp 5.000 / 50 foto Rp 12.000 / 150 foto | E5: Rp 29.000/bulan Rp 249.000/tahun | F5: Rp 500K – 5 Juta / bulan (Custom)
B6: Jumlah Foto | C6: 5 foto/hari (client-side) | D6: 50 foto/pack (90 hari) | E6: Unlimited (avg 120/bln) | F6: Unlimited + Batch Async
B7: Mode Proses | C7: Client-side TF.js (browser) | D7: Server-side PGD (standard) | E7: CA-PGD + Ensemble (full 4A Shield) | F7: CA-PGD + Ensemble + Dedicated API
B8: Resolusi Maksimum | C8: 1080p | D8: 4K | E8: 8K | F8: Unlimited
B9: Athena Seal | C9: Tidak | D9: Tidak | E9: Ya (forensik) | F9: Ya + Custom
B10: Watermark ATHENA | C10: Ya | D10: Tidak | E10: Tidak | F10: Tidak (white-label)
B11: Waktu Proses | C11: 30-90 detik | D11: 15-45 detik | E11: 15-45 detik | F11: Async + notif
B12: Batch Upload | C12: Tidak | D12: Tidak | E12: Max 20 foto | F12: Max 500 foto
B13: SLA Uptime | C13: Best effort | D13: Best effort | E13: 99.5% | F13: 99.9%
B14: Priority Support | C14: Tidak | D14: Tidak | E14: Email 48 jam | F14: Dedicated + WhatsApp
B15: Invoice Resmi | C15: Tidak | D15: Tidak | E15: Tidak | F15: Ya
B16: Target Pengguna | C16: Pelajar, coba awareness | D16: UMKM occasional Kreator sesekali | E16: Kreator aktif Fotografer | F16: UMKM menengah Agensi kreatif
B19: ANALISIS MARGIN PER TIER
B20: HPP per foto (rata-rata) | C20: Rp 0 | D20: =HPP_UNIT!B11 -> 104.9 | E20: =HPP_UNIT!B30 -> 232 | F20: Estimasi Rp 175 (custom)
B21: Harga Jual per foto | C21: Rp 0 | D21: =ASUMSI!C36/50 -> 100 | E21: =ASUMSI!C37/120 -> 241.66667 | F21: Custom quote
B22: Gross Margin (%) | C22: N/A | D22: =HPP_UNIT!B17 -> -0.049 | E22: =HPP_UNIT!B32 -> 0.04 | F22: >60%
B23: Potensi Revenue/bulan | C23: Rp 0 (funnel) | D23: =ASUMSI!C36*ASUMSI!C25*0.2 -> 200000 | E23: =ASUMSI!C37*ASUMSI!C25*0.09 -> 522000 | F23: =ASUMSI!C39*ASUMSI!C25*0.01 -> 1000000

Sheet PROYEKSI_12_BULAN
A1: PROYEKSI KEUANGAN 12 BULAN - ATHENA (Nov 2026 - Okt 2027)
A2: Semua nilai dalam Rupiah (Rp). Skenario: Moderat. Formula otomatis dari sheet ASUMSI.
A4: Bulan | B4: User Total | C4: User Berbayar | D4: Transaksi | E4: Gross Revenue | F4: Total HPP | G4: Gross Profit | H4: Fixed Cost | I4: Net Profit | J4: Pertumbuhan Rev
A5: Nov 2026 | B5: 200 | C5: 60 | D5: 72 | E5: 1008000 | F5: 766080 | G5: 241920 | H5: 750000 | I5: -508080 | J5: N/A
A6: Des 2026 | B6: =ROUND(B5*1.14,0) -> 228 | C6: =ROUND(B6*0.3,0) -> 68 | D6: =ROUND(C6*1.2,0) -> 82 | E6: =D6*14000 -> 1148000 | F6: =ROUND(E6*0.76,0) -> 872480 | G6: =E6-F6 -> 275520 | H6: =750000+ROUND(B6*100,0) -> 772800 | I6: =G6-H6 -> -497280 | J6: =IF(E5>0,(E6-E5)/E5,0) -> 0.13888889
A7: Jan 2027 | B7: =ROUND(B6*1.14,0) -> 260 | C7: =ROUND(B7*0.3,0) -> 78 | D7: =ROUND(C7*1.2,0) -> 94 | E7: =D7*14000 -> 1316000 | F7: =ROUND(E7*0.76,0) -> 1000160 | G7: =E7-F7 -> 315840 | H7: =750000+ROUND(B7*100,0) -> 776000 | I7: =G7-H7 -> -460160 | J7: =IF(E6>0,(E7-E6)/E6,0) -> 0.14634146
A8: Feb 2027 | B8: =ROUND(B7*1.14,0) -> 296 | C8: =ROUND(B8*0.3,0) -> 89 | D8: =ROUND(C8*1.2,0) -> 107 | E8: =D8*14000 -> 1498000 | F8: =ROUND(E8*0.76,0) -> 1138480 | G8: =E8-F8 -> 359520 | H8: =750000+ROUND(B8*100,0) -> 779600 | I8: =G8-H8 -> -420080 | J8: =IF(E7>0,(E8-E7)/E7,0) -> 0.13829787
A9: Mar 2027 | B9: =ROUND(B8*1.14,0) -> 337 | C9: =ROUND(B9*0.3,0) -> 101 | D9: =ROUND(C9*1.2,0) -> 121 | E9: =D9*14000 -> 1694000 | F9: =ROUND(E9*0.76,0) -> 1287440 | G9: =E9-F9 -> 406560 | H9: =750000+ROUND(B9*100,0) -> 783700 | I9: =G9-H9 -> -377140 | J9: =IF(E8>0,(E9-E8)/E8,0) -> 0.13084112
A10: Apr 2027 | B10: =ROUND(B9*1.14,0) -> 384 | C10: =ROUND(B10*0.3,0) -> 115 | D10: =ROUND(C10*1.2,0) -> 138 | E10: =D10*14000 -> 1932000 | F10: =ROUND(E10*0.76,0) -> 1468320 | G10: =E10-F10 -> 463680 | H10: =750000+ROUND(B10*100,0) -> 788400 | I10: =G10-H10 -> -324720 | J10: =IF(E9>0,(E10-E9)/E9,0) -> 0.14049587
A11: Mei 2027 | B11: =ROUND(B10*1.14,0) -> 438 | C11: =ROUND(B11*0.3,0) -> 131 | D11: =ROUND(C11*1.2,0) -> 157 | E11: =D11*14000 -> 2198000 | F11: =ROUND(E11*0.76,0) -> 1670480 | G11: =E11-F11 -> 527520 | H11: =750000+ROUND(B11*100,0) -> 793800 | I11: =G11-H11 -> -266280 | J11: =IF(E10>0,(E11-E10)/E10,0) -> 0.13768116
A12: Jun 2027 | B12: =ROUND(B11*1.14,0) -> 499 | C12: =ROUND(B12*0.3,0) -> 150 | D12: =ROUND(C12*1.2,0) -> 180 | E12: =D12*14000 -> 2520000 | F12: =ROUND(E12*0.76,0) -> 1915200 | G12: =E12-F12 -> 604800 | H12: =750000+ROUND(B12*100,0) -> 799900 | I12: =G12-H12 -> -195100 | J12: =IF(E11>0,(E12-E11)/E11,0) -> 0.14649682
A13: Jul 2027 | B13: =ROUND(B12*1.14,0) -> 569 | C13: =ROUND(B13*0.3,0) -> 171 | D13: =ROUND(C13*1.2,0) -> 205 | E13: =D13*14000 -> 2870000 | F13: =ROUND(E13*0.76,0) -> 2181200 | G13: =E13-F13 -> 688800 | H13: =750000+ROUND(B13*100,0) -> 806900 | I13: =G13-H13 -> -118100 | J13: =IF(E12>0,(E13-E12)/E12,0) -> 0.13888889
A14: Ags 2027 | B14: =ROUND(B13*1.14,0) -> 649 | C14: =ROUND(B14*0.3,0) -> 195 | D14: =ROUND(C14*1.2,0) -> 234 | E14: =D14*14000 -> 3276000 | F14: =ROUND(E14*0.76,0) -> 2489760 | G14: =E14-F14 -> 786240 | H14: =750000+ROUND(B14*100,0) -> 814900 | I14: =G14-H14 -> -28660 | J14: =IF(E13>0,(E14-E13)/E13,0) -> 0.14146341
A15: Sep 2027 | B15: =ROUND(B14*1.14,0) -> 740 | C15: =ROUND(B15*0.3,0) -> 222 | D15: =ROUND(C15*1.2,0) -> 266 | E15: =D15*14000 -> 3724000 | F15: =ROUND(E15*0.76,0) -> 2830240 | G15: =E15-F15 -> 893760 | H15: =750000+ROUND(B15*100,0) -> 824000 | I15: =G15-H15 -> 69760 | J15: =IF(E14>0,(E15-E14)/E14,0) -> 0.13675214
A16: Okt 2027 | B16: =ROUND(B15*1.14,0) -> 844 | C16: =ROUND(B16*0.3,0) -> 253 | D16: =ROUND(C16*1.2,0) -> 304 | E16: =D16*14000 -> 4256000 | F16: =ROUND(E16*0.76,0) -> 3234560 | G16: =E16-F16 -> 1021440 | H16: =750000+ROUND(B16*100,0) -> 834400 | I16: =G16-H16 -> 187040 | J16: =IF(E15>0,(E16-E15)/E15,0) -> 0.14285714
A17: TOTAL / RATA-RATA | B17: =AVERAGE(B5:B16) -> 453.66667 | C17: =AVERAGE(C5:C16) -> 136.08333 | D17: =AVERAGE(D5:D16) -> 163.33333 | E17: =SUM(E5:E16) -> 27440000 | F17: =SUM(F5:F16) -> 20854400 | G17: =SUM(G5:G16) -> 6585600 | H17: =SUM(H5:H16) -> 9524400 | I17: =SUM(I5:I16) -> -2938800 | J17: =AVERAGE(J6:J16) -> 0.13990952

Sheet RINGKASAN_FIKSI
B1: RINGKASAN EVALUASI FIKSI 2026 - ATHENA
B2: Ringkasan ini disiapkan khusus untuk kebutuhan penilaian Kategori Rencana Usaha FIKSI 2026
B5: MASALAH YANG DISELESAIKAN
B6: Setiap hari lebih dari 40 juta foto diunggah pengguna Indonesia ke platform digital. Tanpa sepengetahuan mereka, foto tersebut di-scrape secara otomatis oleh perusahaan AI global untuk melatih model, mulai dari pengenalan wajah, deepfake generator, hingga AI generatif yang meniru motif budaya lokal. Dampaknya: (1) Perempuan dan pelajar rentan terhadap KBGO digital; (2) Pengrajin batik, tenun, dan ukiran kehilangan hak kekayaan intelektual visual mereka; (3) Tidak ada solusi lokal yang terjangkau dan mudah digunakan untuk masalah ini.
B8: SOLUSI YANG DITAWARKAN
B9: ATHENA adalah platform SaaS pertama di Indonesia yang memungkinkan siapa pun melindungi foto dan karya visual dari eksploitasi AI menggunakan teknologi 4A Shield (Anti-AI, Anti-NSFW, Anti-Deepfake, Anti-Training). Dengan arsitektur tiga jalur: free tier client-side, paid tier server-side CA-PGD+Ensemble, dan enterprise batch async, ATHENA menjawab kebutuhan dari pelajar individual hingga UMKM kreatif dengan model biaya yang terjangkau.
B11: KEUNGGULAN KOMPETITIF
B12: 1. Pertama di Indonesia: tidak ada kompetitor lokal yang fokus pada perlindungan visual berbasis AI. 2. Kearifan lokal terintegrasi: Anti-Training khusus untuk motif batik, tenun, ukiran, bukan sekadar produk barat yang dilokalisasi. 3. Free tier tanpa GPU server cost: foto diproses di browser pengguna, privacy paradox hilang otomatis. 4. Model bisnis yang scalable: dari Rp 0 hingga enterprise custom pricing. 5. Dasar ilmiah yang terverifikasi: bukan klaim marketing, tapi reproduksi teknik yang sudah dipublikasikan (Glaze 2023, Nightshade 2023, Witches Brew 2021).
B14: RELEVANSI DENGAN TEMA FIKSI 2026
B15: ATHENA mengintegrasikan dua pilar utama FIKSI 2026 secara langsung: (1) Teknologi Digital: penggunaan adversarial machine learning, compression-aware PGD, dan ensemble surrogate model adalah aplikasi nyata AI untuk kepentingan sosial Indonesia; (2) Ekonomi Kreatif Berbasis Kearifan Lokal: perlindungan motif batik, tenun ikat, wayang, dan kerajinan lokal dari eksploitasi AI generatif global adalah bentuk konkret pertahanan ekonomi kreatif Indonesia di era AI. Tidak ada proyek lain dalam kompetisi ini yang menjawab kedua pilar ini sekaligus secara teknis dan bisnis.
B17: ALASAN PRODUK LAYAK MASUK TAHAP PERENCANAAN USAHA
B18: ATHENA layak karena: (1) Masalah nyata, bukan spekulatif: data KBGO digital meningkat, eksploitasi AI terhadap karya lokal terdokumentasi; (2) Solusi teknis tervalidasi: bukan prototipe baru, melainkan implementasi teknik yang sudah terbukti dalam riset akademis; (3) Model biaya realistis: ATHENA bisa diluncurkan dengan modal kurang dari Rp 1 juta/bulan di bulan pertama; (4) Target pasar jelas dan terukur: 40 juta pengunggah foto per hari di Indonesia = addressable market yang sangat besar; (5) Tim dengan kapabilitas nyata: siswa PPLG dengan stack React + Node.js + Python yang relevan dan sudah berpengalaman membangun proyek nyata.
... B21: Model HPP ATHENA dibangun di atas tiga prinsip akuntabilitas: (1) Semua asumsi biaya bersumber dari pricing page layanan cloud aktual (Replicate.com, Cloudflare R2, Midtrans, Railway.app), bukan estimasi generik; (2) Struktur biaya variabel dominan berarti HPP tidak melonjak tanpa ada pendapatan yang mengimbangi; (3) Skenario konservatif, moderat, dan optimistis masing-masing menunjukkan bahwa produk tetap viable meski realitas meleset 30-40% dari target. Ini adalah proposal yang jujur tentang biaya sebenarnya, bukan angka yang dibuat terlihat bagus untuk lomba.

Sheet DASHBOARD
B1: DASHBOARD EKSEKUTIF - ATHENA FIKSI 2026
B2: Ringkasan visual profesional untuk penilaian juri — semua angka formula otomatis
B5: HPP per Foto (Kredit) | D5: HPP per Foto (Pro) | F5: Gross Margin (Pro) | H5: Laba per 1.000 Foto (Pro)
B6: =HPP_UNIT!B11 -> 104.9 | D6: =HPP_UNIT!B30 -> 232 | F6: =HPP_UNIT!B32 -> 0.04 | H6: =HPP_UNIT!D31 -> 57666.667
B7: Biaya variabel server-side tier kredit | D7: Biaya CA-PGD+Ensemble per foto | F7: Margin kotor tier Pro skenario moderat | H7: Laba kotor pada volume 1.000 foto Pro
B9: Target User Thn 1 | D9: Break-even User Berbayar | F9: Total HPP Fixed/Bulan | H9: Proyeksi Revenue Thn 1
B10: =ASUMSI!C26 -> 1500 | D10: 50 | F10: =SUM(ASUMSI!C16:C22) -> 750000 | H10: =PROYEKSI_12_BULAN!E17 -> 27440000
B11: User aktif akhir bulan ke-12 | D11: Minimum user berbayar untuk tutup fixed cost | F11: Total biaya tetap infrastruktur per bulan | H11: Total gross revenue 12 bulan pertama
B13: PERBANDINGAN SKENARIO - GROSS MARGIN PER TIER
C14: Optimistis | E14: Moderat | G14: Konservatif
B15: Gross Margin Kredit | D15: =HPP_SCENARIO!B21 -> 0.28 | F15: =HPP_SCENARIO!C21 -> -0.02 | H15: =HPP_SCENARIO!D21 -> -0.57
B16: Gross Margin Pro | D16: =HPP_SCENARIO!B22 -> 0.16206897 | F16: =HPP_SCENARIO!C22 -> 0.08137931 | H16: =HPP_SCENARIO!D22 -> 0.12551724
B17: Laba per 1K Foto (Kredit) | D17: =HPP_SCENARIO!B23 -> 28000 | F17: =HPP_SCENARIO!C23 -> -2000 | H17: =HPP_SCENARIO!D23 -> -57000
B18: Laba per 1K Foto (Pro) | D18: =HPP_SCENARIO!B24 -> 31333.333 | F18: =HPP_SCENARIO!C24 -> 19666.667 | H18: =HPP_SCENARIO!D24 -> 45500
B20: VISUALISASI TREN PERTUMBUHAN REVENUE (12 BULAN)
B41: ATHENA - Platform Perlindungan Visual Berbasis AI | FIKSI 2026 | Dokumen Finansial v1.0
